perutils/__init__.py
perutils/_nbdev.py
perutils/core.py
perutils/kaggle.py
perutils/nbutils.py
perutils/splitting.py
perutils/tabutils.py
perutils/tracking.py
perutils-0.0.23.dist-info/LICENSE
perutils-0.0.23.dist-info/METADATA
perutils-0.0.23.dist-info/WHEEL
perutils-0.0.23.dist-info/entry_points.txt
perutils-0.0.23.dist-info/top_level.txt
perutils-0.0.23.dist-info/RECORD
