Metadata-Version: 2.1
Name: perutils
Version: 0.0.23
Summary: Isaacs personal utils
Home-page: https://github.com/Isaac.Flath@gmail.com/perutils/tree/{branch}/
Author: Isaac Flath
Author-email: Isaac.Flath@gmail.com
License: Apache Software License 2.0
Keywords: some keywords
Platform: UNKNOWN
Classifier: Development Status :: 3 - Alpha
Classifier: Intended Audience :: Developers
Classifier: Natural Language :: English
Classifier: Programming Language :: Python :: 3.6
Classifier: Programming Language :: Python :: 3.7
Classifier: Programming Language :: Python :: 3.8
Classifier: License :: OSI Approved :: Apache Software License
Requires-Python: >=3.6
Requires-Dist: pandas
Requires-Dist: fastai
